awslambda/__init__.py
awslambda/deploy.py
awslambda-1.0.6.dist-info/DESCRIPTION.rst
awslambda-1.0.6.dist-info/METADATA
awslambda-1.0.6.dist-info/RECORD
awslambda-1.0.6.dist-info/WHEEL
awslambda-1.0.6.dist-info/entry_points.txt
awslambda-1.0.6.dist-info/metadata.json
awslambda-1.0.6.dist-info/top_level.txt
