Metadata-Version: 2.0
Name: awslambda
Version: 1.0.6
Summary: A tool for deploying Python projects to AWS Lambda.
Home-page: https://github.com/pgorczak/awslambda
Author: Philipp Gorczak
Author-email: p.gorczak@gmail.com
License: GPLv3
Keywords: aws lambda
Platform: UNKNOWN
Classifier: Environment :: Console
Classifier: Intended Audience :: Developers
Classifier: License :: OSI Approved :: GNU General Public License v3 (GPLv3)
Classifier: Programming Language :: Python :: 2.7
Classifier: Topic :: Internet :: WWW/HTTP :: Site Management
Classifier: Topic :: System :: Software Distribution
Classifier: Topic :: Utilities
Requires-Dist: boto3
Requires-Dist: click
Requires-Dist: PyYAML
